setup.py
distributions_gandb/Binomialdistribution.py
distributions_gandb/Gaussiandistribution.py
distributions_gandb/Generaldistribution.py
distributions_gandb/__init__.py
distributions_gandb.egg-info/PKG-INFO
distributions_gandb.egg-info/SOURCES.txt
distributions_gandb.egg-info/dependency_links.txt
distributions_gandb.egg-info/not-zip-safe
distributions_gandb.egg-info/top_level.txt