Metadata-Version: 1.0
Name: distributions-gandb
Version: 0.1
Summary: Gaussian and Binomial distributions
Home-page: UNKNOWN
Author: Siddhesh More
Author-email: UNKNOWN
License: UNKNOWN
Platform: UNKNOWN
